Workbook

Sheet Invoice Data
B2: Invoice Data Entry – PDF / Scan to Excel
B3: Typed from the scanned invoice in the 'Source Invoice' sheet. Fictional supplier and figures – sample portfolio file.
B5: Supplier | C5: Al-Bayan Office Supplies
B6: Invoice No. | C6: INV-2026-0418
B7: Invoice date | C7: 46279
B8: Customer | C8: Shelter Camps Admin Office
B9: Currency | C9: USD ($)
B11: # | C11: Description | D11: Unit | E11: Qty | F11: Unit Price ($) | G11: Amount ($)
B12: 1 | C12: A4 Copy Paper 80gsm (500 sheets) | D12: Ream | E12: 40 | F12: 4.25 | G12: =E12*F12 -> 170
B13: 2 | C13: Blue Ballpoint Pens (box of 50) | D13: Box | E13: 6 | F13: 7.8 | G13: =E13*F13 -> 46.8
B14: 3 | C14: Spiral Notebook A5, 100 pages | D14: Piece | E14: 120 | F14: 0.95 | G14: =E14*F14 -> 114
B15: 4 | C15: Stapler, heavy duty | D15: Piece | E15: 8 | F15: 6.4 | G15: =E15*F15 -> 51.2
B16: 5 | C16: Staples No. 24/6 (box of 1000) | D16: Box | E16: 15 | F16: 1.2 | G16: =E16*F16 -> 18
B17: 6 | C17: Box File, A4 | D17: Piece | E17: 30 | F17: 2.35 | G17: =E17*F17 -> 70.5
B18: 7 | C18: Printer Toner HP 85A (compatible) | D18: Piece | E18: 5 | F18: 24.9 | G18: =E18*F18 -> 124.5
B19: 8 | C19: Whiteboard Markers (set of 4) | D19: Set | E19: 12 | F19: 3.6 | G19: =E19*F19 -> 43.2
B20: 9 | C20: Correction Tape | D20: Piece | E20: 25 | F20: 1.1 | G20: =E20*F20 -> 27.5
B21: 10 | C21: Plastic Sheet Protectors (pack of 100) | D21: Pack | E21: 10 | F21: 4.75 | G21: =E21*F21 -> 47.5
B22: 11 | C22: Calculator, 12-digit | D22: Piece | E22: 6 | F22: 8.5 | G22: =E22*F22 -> 51
B23: 12 | C23: Envelopes A4, brown (pack of 50) | D23: Pack | E23: 8 | F23: 5.3 | G23: =E23*F23 -> 42.4
... B26: 15 | C26: Desk Organizer, mesh | D26: Piece | E26: 4 | F26: 9.75 | G26: =E26*F26 -> 39
C28: Blue = values typed from the invoice; black = formulas. | F28: Subtotal | G28: =SUM(G12:G26) -> 948.6
C29: Rates as printed on the invoice (Discount 5%, VAT 16%). | F29: Discount rate | G29: 0.05
F30: Discount | G30: =-ROUND(G28*G29,2) -> -47.43
F31: Net | G31: =G28+G30 -> 901.17
F32: VAT rate | G32: 0.16
F33: VAT | G33: =ROUND(G31*G32,2) -> 144.19
F34: TOTAL ($) | G34: =G31+G33 -> 1045.36

Sheet Accuracy Check
B2: Accuracy check – typed data vs. totals printed on the invoice
B4: Field | C4: Printed on invoice | D4: Calculated in Excel | E4: Difference | F4: Result
B5: Subtotal | C5: 948.6 | D5: ='Invoice Data'!G28 -> 948.6 | E5: =ROUND(D5-C5,2) -> 0 | F5: =IF(ABS(E5)<0.01,"Match","Check") -> Match
B6: Discount | C6: -47.43 | D6: ='Invoice Data'!G30 -> -47.43 | E6: =ROUND(D6-C6,2) -> 0 | F6: =IF(ABS(E6)<0.01,"Match","Check") -> Match
B7: Net | C7: 901.17 | D7: ='Invoice Data'!G31 -> 901.17 | E7: =ROUND(D7-C7,2) -> 0 | F7: =IF(ABS(E7)<0.01,"Match","Check") -> Match
B8: VAT | C8: 144.19 | D8: ='Invoice Data'!G33 -> 144.19 | E8: =ROUND(D8-C8,2) -> 0 | F8: =IF(ABS(E8)<0.01,"Match","Check") -> Match
B9: TOTAL | C9: 1045.36 | D9: ='Invoice Data'!G34 -> 1045.36 | E9: =ROUND(D9-C9,2) -> 0 | F9: =IF(ABS(E9)<0.01,"Match","Check") -> Match
B10: Number of lines | C10: 15 | D10: =COUNTA('Invoice Data'!C12:C26) -> 15 | E10: =ROUND(D10-C10,2) -> 0 | F10: =IF(ABS(E10)<0.01,"Match","Check") -> Match
B12: Overall | C12: =IF(COUNTIF(F5:F10,"Match")=6,"All 6 checks match – 100% accurate","Review needed") -> All 6 checks match – 100% accurate
B14: Printed values (blue) are copied from the invoice footer; calculated values (green) link to the 'Invoice Data' sheet.

Sheet Source Invoice
B2: Source document (scanned invoice – fictional)
